allauth_suap/__init__.py
allauth_suap/apps.py
allauth_suap/provider.py
allauth_suap/tests.py
allauth_suap/urls.py
allauth_suap/views.py
django_allauth_suap-0.1.2.dist-info/METADATA
django_allauth_suap-0.1.2.dist-info/WHEEL
django_allauth_suap-0.1.2.dist-info/licenses/LICENSE
django_allauth_suap-0.1.2.dist-info/RECORD
